{
    "_updated": "2021-10-25",
    "label": "渋谷重長",
    "list": [
        {
            "label": "20　　(年未詳)正月　日　_渋谷重長請文案（＃１４０）",
            "name": "宮内少輔重長",
            "objectID": "140"
        },
        {
            "label": "21　　(年未詳)8月4日　　_市来家親書状（＃１４１）",
            "name": "清色",
            "objectID": "141"
        },
        {
            "label": "22　　応永24年9月20日　　伊集院道応(頼久)知行充行状（＃１４２）",
            "name": "清色",
            "objectID": "142"
        },
        {
            "label": "10　　嘉吉元年2月27日　　渋谷重長譲状（＃８５）",
            "name": "弾正少弼重長",
            "objectID": "85"
        },
        {
            "label": "11　　応永13年11月15日　_渋谷重頼譲状（＃８６）",
            "name": "菊五郎",
            "objectID": "86"
        },
        {
            "label": "12　　応永30年8月16日　　渋谷重長譲状（＃８７）",
            "name": "重長",
            "objectID": "87"
        }
    ],
    "objectID": "渋谷重長"
}